.gitignore
LICENSE
README.md
app.py
requirements.txt
setup.cfg
setup.py
api/resource/application-dell-development.yml
api/resource/application-dev.yml
api/resource/application-local.yml
api/resource/application.yml
api/src/NotificationManagerApi.py
api/src/client/emitter/TelegramEmitter.py
api/src/client/emitter/VoiceEmitter.py
api/src/client/listener/NotificationManagerListener.py
api/src/config/NotificationManagerConfig.py
api/src/config/QueueConfig.py
api/src/controller/NotificationController.py
api/src/enumeration/ApiKeyContext.py
api/src/helper/static/TextStaticHelper.py
api/src/mapper/NotificationManagerMapper.py
api/src/model/ModelAssociation.py
api/src/model/Notification.py
api/src/repository/NotificationManagerRepository.py
api/src/service/EmailService.py
api/src/service/NotificationManagerService.py
api/src/service/TelegramService.py
api/src/service/VoiceService.py
notification_manager_api/__init__.py
notification_manager_api.egg-info/PKG-INFO
notification_manager_api.egg-info/SOURCES.txt
notification_manager_api.egg-info/dependency_links.txt
notification_manager_api.egg-info/requires.txt
notification_manager_api.egg-info/top_level.txt
notification_manager_api/api/src/config/NotificationConfig.py
notification_manager_api/api/src/constant/NotificationConfigurationKeyConstant.py
notification_manager_api/api/src/constant/NotificationConstant.py
notification_manager_api/api/src/converter/static/NotificationStaticConverter.py
notification_manager_api/api/src/dto/NotificationDto.py
notification_manager_api/api/src/enumeration/NotificationDestiny.py
notification_manager_api/api/src/enumeration/NotificationSeverity.py
notification_manager_api/api/src/enumeration/NotificationStatus.py
notification_manager_api/api/src/manager/NotificationManager.py
notification_manager_api/api/src/provider/client/emitter/NotificationEmitterProvider.py
notification_manager_api/api/src/provider/service/NotificationServiceProvider.py
notification_manager_api/api/src/provider/validator/NotificationValidatorProvider.py