Metadata-Version: 2.1
Name: notification-manager-api
Version: 0.0.13
Summary: Queue Manager
Home-page: https://github.com/SamuelJansen/notification-manager-api/
Download-URL: https://github.com/SamuelJansen/notification-manager-api/archive/v0.0.13.tar.gz
Author: Samuel Jansen
Author-email: samuel.jansenn@gmail.com
License: MIT
Keywords: queue,topic
Classifier: Development Status :: 3 - Alpha
Classifier: Intended Audience :: Developers
Classifier: Topic :: Software Development :: Build Tools
Classifier: License :: OSI Approved :: MIT License
Classifier: Programming Language :: Python :: 3.7
Requires-Python: >=3.7
License-File: LICENSE
